textglue/.gitignore
textglue/__init__.py
textglue/textglue.py
textglue-0.0.5.dist-info/METADATA
textglue-0.0.5.dist-info/WHEEL
textglue-0.0.5.dist-info/entry_points.txt
textglue-0.0.5.dist-info/licenses/LICENSE
textglue-0.0.5.dist-info/RECORD
