Metadata-Version: 2.4
Name: textglue
Version: 0.0.5
Summary: textglue - An simple static template system
Project-URL: Homepage, https://gitlab.com/derekmc/derekmc.gitlab.io/-/tree/main/projects/textglue
Project-URL: Issues, https://gitlab.com/derekmc/derekmc.gitlab.io/-/tree/main/projects/textglue
Author-email: derekmc <derek7mc@gmail.com>
License-Expression: MIT
License-File: LICENSE
Classifier: Operating System :: OS Independent
Classifier: Programming Language :: Python :: 3
Requires-Python: >=3.9
